{"id":"640764470d15d31b770ba90d","title":"Cabin Của Tiến Sĩ Caligari","origin_name":"Das Cabinet des Dr. Caligari","slug":"cabin-cua-tien-si-caligari","thumb":"https://cdn.jsdelivr.net/gh/gotvtop102/goimg102@main/public/thumbs/ca/cabin-cua-tien-si-caligari.webp","poster":"https://cdn.jsdelivr.net/gh/gotvtop102/goimg102@main/public/posters/ca/cabin-cua-tien-si-caligari.webp","year":"1920","type":"single","genre":[{"name":"Hình Sự","slug":"hinh-su"},{"name":"Kinh Dị","slug":"kinh-di"},{"name":"Chính kịch","slug":"chinh-kich"},{"name":"Bí ẩn","slug":"bi-an"}],"country":[{"name":"Đức","slug":"duc"}],"lang_key":"Vietsub","episode_current":"Full","quality":"HD","modified":"2023-03-07T23:21:03.000Z","is_4k":false,"is_exclusive":false,"status":"completed","showtimes":"","chieurap":false,"sub_docquyen":false,"episodes":[{"name":"Vietsub #1","slug":"vietsub-1","server_name":"Vietsub #1","server_data":[{"name":"Full","slug":"full","link_embed":"https://vip.opstream14.com/share/72982428d01535343fdf507be3dabb02","link_m3u8":"https://vip.opstream14.com/20230307/33505_cca5d67f/index.m3u8"}]}],"description":"Francis, một chàng trai trẻ, nhớ lại trong ký ức của mình những trải nghiệm khủng khiếp mà anh và vị hôn thê Jane đã trải qua gần đây. Francis và người bạn Alan của anh ấy đến thăm Nội các của Tiến sĩ Caligari, một cuộc triển lãm nơi vị bác sĩ bí ẩn cho Cesare, người mộng du xem, và đánh thức anh ta trong giây lát sau giấc ngủ như chết.","tmdb_id":234,"cast":[],"director":[],"keywords":[],"tmdb":{"id":234},"cast_meta":[],"tmdb_checked":false,"pubjs_url":"https://cdn.jsdelivr.net/gh/gotvtop102/pjs102@main/pubjs/ca/cabin-cua-tien-si-caligari.json"}