{"id":"63e4ffff58c24ebd79211704","title":"Phỉ Thúy Minh Châu","origin_name":"The Jade and the Pearl","slug":"phi-thuy-minh-chau","thumb":"https://cdn.jsdelivr.net/gh/gotvtop102/goimg102@main/public/thumbs/ph/phi-thuy-minh-chau.webp","poster":"https://cdn.jsdelivr.net/gh/gotvtop102/goimg102@main/public/posters/ph/phi-thuy-minh-chau.webp","year":"2010","type":"single","genre":[{"name":"Tình Cảm","slug":"tinh-cam"},{"name":"Hài Hước","slug":"hai-huoc"}],"country":[{"name":"Trung Quốc","slug":"trung-quoc"},{"name":"Hồng Kông","slug":"hong-kong"}],"lang_key":"Vietsub","episode_current":"Full","quality":"HD","modified":"2023-02-09T21:15:27.000Z","is_4k":false,"is_exclusive":false,"status":"completed","showtimes":"","chieurap":false,"sub_docquyen":false,"episodes":[{"name":"Vietsub #1","slug":"vietsub-1","server_name":"Vietsub #1","server_data":[{"name":"Full","slug":"full","link_embed":"https://vip.opstream14.com/share/1baba510b5b8db4473eb73e7b9784b20","link_m3u8":"https://vip.opstream14.com/20230209/30860_23feafa0/index.m3u8"}]}],"description":"<p>Trong hành trình dài đến một vùng đất xa lạ cho cuộc hôn nhân trong mơ của mình, Công chúa Yan (Thái Trác Nghiên) phát hiện ra mình phải lòng Tướng quân Cheng (Lâm Phong), người đang dẫn đầu đoàn quân hộ tống. Bất chấp tình yêu bị ngăn cấm, họ trao đổi những biểu tượng tình yêu. Tuy nhiên, một cuộc tấn công bất ngờ của một băng đảng cướp đã thay đổi vận mệnh của họ. Tướng quân Cheng bị bắt làm con tin bởi nữ thủ lĩnh của băng cướp, Zhu (Joey Yung) và anh dần yêu cô. Bi kịch tiếp tục diễn ra khi Cheng phải đối mặt với những quyết định khó khăn.</p>","tmdb_id":46129,"cast":[],"director":[],"keywords":[],"tmdb":{"id":46129},"cast_meta":[],"tmdb_checked":false,"pubjs_url":"https://cdn.jsdelivr.net/gh/gotvtop102/pjs102@main/pubjs/ph/phi-thuy-minh-chau.json"}