{"id":"63df2969caf0f6e22aad2e52","title":"The Killing","origin_name":"The Killing","slug":"the-killing","thumb":"https://cdn.jsdelivr.net/gh/gotvtop102/goimg102@main/public/thumbs/th/the-killing.webp","poster":"https://cdn.jsdelivr.net/gh/gotvtop102/goimg102@main/public/posters/th/the-killing.webp","year":"1956","type":"single","genre":[{"name":"Hình Sự","slug":"hinh-su"},{"name":"Chính kịch","slug":"chinh-kich"},{"name":"Bí ẩn","slug":"bi-an"}],"country":[{"name":"Âu Mỹ","slug":"au-my"}],"lang_key":"Vietsub","episode_current":"Full","quality":"HD","modified":"2023-02-05T10:58:33.000Z","is_4k":false,"is_exclusive":false,"status":"completed","showtimes":"","chieurap":false,"sub_docquyen":false,"episodes":[{"name":"Vietsub #1","slug":"vietsub-1","server_name":"Vietsub #1","server_data":[{"name":"Full","slug":"full","link_embed":"https://vip.opstream14.com/share/f9d6b4b6c27bc520071ac934b5845e50","link_m3u8":"https://vip.opstream14.com/20230204/30224_ea4c7fe1/index.m3u8"}]}],"description":"<p>Tên tội phạm chuyên nghiệp Johnny Clay tuyển dụng một tay súng cừ khôi, một sĩ quan cảnh sát quanh co, một nhân viên pha chế rượu và một nhân viên cá cược tên George, trong số những người khác, cho một công việc cuối cùng trước khi anh ta đi thẳng và kết hôn. Nhưng khi George nói với người vợ bồn chồn của mình về âm mưu đánh cắp hàng triệu USD từ trường đua nơi anh làm việc, cô ấy đã ấp ủ một âm mưu của riêng mình.</p>","tmdb_id":247,"cast":[],"director":[],"keywords":[],"tmdb":{"id":247},"cast_meta":[],"tmdb_checked":false,"pubjs_url":"https://cdn.jsdelivr.net/gh/gotvtop102/pjs102@main/pubjs/th/the-killing.json"}