{"id":"691e994f83252de8c9dccb95","title":"Nhị Long Hồ Hạo Ca: Thiên Hạ Vô Lại","origin_name":"The Underworld","slug":"the-haoge-of-erlonghu-no-rogues-under-heaven","thumb":"https://cdn.jsdelivr.net/gh/gotvtop102/goimg102@main/public/thumbs/th/the-haoge-of-erlonghu-no-rogues-under-heaven.webp","poster":"https://cdn.jsdelivr.net/gh/gotvtop102/goimg102@main/public/posters/th/the-haoge-of-erlonghu-no-rogues-under-heaven.webp","year":"2025","type":"series","genre":[{"name":"Hài Hước","slug":"hai-huoc"},{"name":"Chính kịch","slug":"chinh-kich"}],"country":[{"name":"Trung Quốc","slug":"trung-quoc"}],"lang_key":"Vietsub","episode_current":"Hoàn tất (24/24)","quality":"HD","modified":"2025-12-11T14:37:30.000Z","is_4k":false,"is_exclusive":false,"status":"completed","showtimes":"","chieurap":false,"sub_docquyen":false,"episodes":[{"name":"Vietsub #1","slug":"vietsub-1","server_name":"Vietsub #1","server_data":[{"name":"1","slug":"1","link_embed":"https://vip.opstream90.com/share/fb4d518989bdeae9784d99c398f86f1f","link_m3u8":"https://vip.opstream90.com/20251120/18081_fb4d5189/index.m3u8"}]}],"description":"<p>Trương Thiên Bá và đội của anh điều hành một công ty đòi nợ chuyên bắt những kẻ lừa đảo và những kẻ vô trách nhiệm. Khi một nữ lừa đảo xảo quyệt gia nhập, họ phải đảm nhận những vụ án nghiêm trọng và đối đầu với một tên tội phạm quyền lực để cứu cô ta và tìm kiếm công lý.</p>","tmdb_id":305364,"cast":["Zhang Hao","Mei Baolai","Zhang Tao","Wang Dongdong","Cui Xiaoyu","Du Xudong","Vu Vinh Quang"],"director":[],"keywords":[],"cast_meta":[{"name":"Zhang Hao","name_vi":null,"name_original":"Zhang Hao","tmdb_id":1996699,"profile":"https://image.tmdb.org/t/p/w500/4BrD1eAqjL3dRQDmbhNUBM2zdob.jpg","tmdb_url":"https://www.themoviedb.org/person/1996699"},{"name":"Mei Baolai","name_vi":null,"name_original":"Mei Baolai","tmdb_id":3314355,"profile":"https://image.tmdb.org/t/p/w500/aN6sVPGfeO2zuvaMvww2WXTL4tL.jpg","tmdb_url":"https://www.themoviedb.org/person/3314355"},{"name":"Zhang Tao","name_vi":null,"name_original":"Zhang Tao","tmdb_id":1996732,"profile":"https://image.tmdb.org/t/p/w500/jkQxAv7xnh91GqulNpdEXolXe3Q.jpg","tmdb_url":"https://www.themoviedb.org/person/1996732"},{"name":"Wang Dongdong","name_vi":null,"name_original":"Wang Dongdong","tmdb_id":2701980,"profile":"https://image.tmdb.org/t/p/w500/yhwzkntjSXU9wjxzMusDuAKq5fo.jpg","tmdb_url":"https://www.themoviedb.org/person/2701980"},{"name":"Cui Xiaoyu","name_vi":null,"name_original":"Cui Xiaoyu","tmdb_id":5809105,"profile":null,"tmdb_url":"https://www.themoviedb.org/person/5809105"},{"name":"Du Xudong","name_vi":null,"name_original":"Du Xudong","tmdb_id":1418127,"profile":"https://image.tmdb.org/t/p/w500/4ieELQhH5dQT1bdsGfBq3WefdyT.jpg","tmdb_url":"https://www.themoviedb.org/person/1418127"},{"name":"Vu Vinh Quang","name_vi":"Vu Vinh Quang","name_original":"Yu Rongguang","tmdb_id":120725,"profile":"https://image.tmdb.org/t/p/w500/qRPhrqPLYvca6Wdv9lMxwEm7ZD6.jpg","tmdb_url":"https://www.themoviedb.org/person/120725"}],"pubjs_url":"https://cdn.jsdelivr.net/gh/gotvtop102/pjs102@main/pubjs/th/the-haoge-of-erlonghu-no-rogues-under-heaven.json"}