{"id":"63e4a1a558c24ebd79150cfc","title":"Cuồng Hổ Nguy Thành","origin_name":"Mutant Tiger","slug":"cuong-ho-nguy-thanh","thumb":"https://cdn.jsdelivr.net/gh/gotvtop102/goimg102@main/public/thumbs/cu/cuong-ho-nguy-thanh.webp","poster":"https://cdn.jsdelivr.net/gh/gotvtop102/goimg102@main/public/posters/cu/cuong-ho-nguy-thanh.webp","year":"2022","type":"single","genre":[{"name":"Phiêu Lưu","slug":"phieu-luu"}],"country":[{"name":"Trung Quốc","slug":"trung-quoc"}],"lang_key":"Vietsub","episode_current":"Full","quality":"HD","modified":"2023-02-09T14:32:53.000Z","is_4k":false,"is_exclusive":false,"status":"completed","showtimes":"","chieurap":false,"sub_docquyen":false,"episodes":[{"name":"Vietsub #1","slug":"vietsub-1","server_name":"Vietsub #1","server_data":[{"name":"Full","slug":"full","link_embed":"https://vip.opstream16.com/share/ce916a6c3a313e568546f66654ee5ee1","link_m3u8":"https://vip.opstream16.com/20230209/30965_73241304/index.m3u8"}]}],"description":"<p>Ming Jiajing trong 37 năm, quyền của thái tử đã thay đổi đối lập. Cho nên Đông xưởng ở nơi hung hổ xuất hiện - tây nam biên giới nhỏ thành lập \"Sư lễ săn trường\", săn hung hổ dùng để luyện hóa. Nhưng không ngờ, động thái này làm cho virus kỳ lạ xâm nhập vào cơ thể hổ, khiến hổ phát điên và hình thành dịch hạch nhanh chóng lan truyền. …… Vào thời điểm này, Zhang Liucheng, một gia đình của Jin Yi Wei bị sa thải, đã mang theo đứa trẻ mồ côi bị gia đình Dongchang tiêu diệt vì đã tố cáo vụ việc, đến nơi này để tìm Zhang Lưuping, em trai của người săn mồi, người đã được tuyển vào khu săn bắn Sili. Nhưng không ngờ bị tấn công bởi những con hổ biến dị. Nhưng khủng hoảng chỉ là bắt đầu, rất nhanh, dịch bệnh làm cho hổ nhanh chóng tập hợp gần trăm con, đem thị trấn thành phố đoàn vây quanh, một thời gian trấn dân liên tiếp bị mãnh hổ giết chóc, toàn thành nguy hiểm ở trong nguy hiểm! Trương Liễu Thành đứng lên ra, chuẩn bị dẫn dắt Hoan Nhi cùng dân chúng trong trấn trốn sinh thiên, nhưng hắn không biết chính là, “Sân săn” trong còn có bí mật kinh thiên hung dữ hơn dã thú. ……</p>","tmdb_id":1024392,"cast":[],"director":[],"keywords":[],"tmdb":{"id":1024392},"cast_meta":[],"tmdb_checked":false,"pubjs_url":"https://cdn.jsdelivr.net/gh/gotvtop102/pjs102@main/pubjs/cu/cuong-ho-nguy-thanh.json"}