{"id":"626d9b863a2c0c6289b8ccb8","title":"Hàng Xóm Quái Dị","origin_name":"1BR","slug":"hang-xom-quai-di","thumb":"https://cdn.jsdelivr.net/gh/gotvtop102/goimg102@main/public/thumbs/ha/hang-xom-quai-di.webp","poster":"https://cdn.jsdelivr.net/gh/gotvtop102/goimg102@main/public/posters/ha/hang-xom-quai-di.webp","year":"2019","type":"single","genre":[{"name":"Tâm Lý","slug":"tam-ly"},{"name":"Kinh Dị","slug":"kinh-di"}],"country":[{"name":"Âu Mỹ","slug":"au-my"}],"lang_key":"Vietsub","episode_current":"Full","quality":"HD","modified":"2023-02-27T17:45:26.000Z","is_4k":false,"is_exclusive":false,"status":"completed","showtimes":"","chieurap":false,"sub_docquyen":false,"episodes":[{"name":"Vietsub #1","slug":"vietsub-1","server_name":"Vietsub #1","server_data":[{"name":"Full","slug":"full","link_embed":"https://vip.opstream15.com/share/d6d0f445ef4338aba648d1a13936743c","link_m3u8":"https://vip.opstream15.com/20220429/10228_6ce2ea1f/index.m3u8"}]}],"description":"<p>Cô gái trẻ Sarah quyết định bắt đầu một cuộc sống mới ở LA, nhưng những người hàng xóm trong khu phức hợp không đơn giản như cô nghĩ.</p>","tmdb_id":611605,"cast":[],"director":[],"keywords":[],"tmdb":{"id":611605},"cast_meta":[],"tmdb_checked":false,"pubjs_url":"https://cdn.jsdelivr.net/gh/gotvtop102/pjs102@main/pubjs/ha/hang-xom-quai-di.json"}