{"id":"69295201a3ee3859477c2070","title":"Đối Tác Hôn Nhân","origin_name":"My Commissioned Lover","slug":"doi-tac-hon-nhan","thumb":"https://cdn.jsdelivr.net/gh/gotvtop102/goimg102@main/public/thumbs/do/doi-tac-hon-nhan.webp","poster":"https://cdn.jsdelivr.net/gh/gotvtop102/goimg102@main/public/posters/do/doi-tac-hon-nhan.webp","year":"2019","type":"series","genre":[{"name":"Hài Hước","slug":"hai-huoc"},{"name":"Chính kịch","slug":"chinh-kich"}],"country":[{"name":"Trung Quốc","slug":"trung-quoc"},{"name":"Hồng Kông","slug":"hong-kong"}],"lang_key":"Lồng Tiếng","episode_current":"Hoàn Tất (20/20)","quality":"HD","modified":"2025-11-28T14:40:49.000Z","is_4k":false,"is_exclusive":false,"status":"completed","showtimes":"","chieurap":false,"sub_docquyen":false,"episodes":[{"name":"Lồng Tiếng #1","slug":"vietsub-1","server_name":"Lồng Tiếng #1","server_data":[{"name":"1","slug":"1","link_embed":"https://vip.opstream17.com/share/64179b3eb67988583d803807ca305acf","link_m3u8":"https://vip.opstream17.com/20251125/23977_64179b3e/index.m3u8"}]}],"description":"<p>Từ một thợ trang trí nội thất, Lãng Triều Dũng (Dương Minh) phất lên nhờ hình thức kinh doanh phòng trọ. Anh cùng Bối Canh Chi (Cao Hải Ninh), nhân viên môi giới nhà đất, gầy dựng công ty địa ốc, thu về lợi nhuận khổng lồ chỉ trong vài năm. Họ đặt ra mục tiêu phải trở thành đầu tàu của ngành bất động sản. Dũng và Chi bên nhau từ khi tay trắng, họ yêu nhau và tiến tới cuộc sống hôn nhân. Đến lúc này, quan niệm khác biệt về gia đình của Dũng và Chi mới thực sự bộc lộ. Dũng cho rằng tình thân là điều quan trọng nhất. Chính vì vậy, anh ta luôn dành nhiều tâm sức, tiền của để dung túng cho bạn bè và các thành viên bên nhà mình. Trong đó có em trai Lãng Triều Nhân (Lục Vĩnh) và em gái Lãng Triều Tín (Thang Lạc Văn). Trong khi đó, Chi từng trải qua quá khứ không hạnh phúc. Cô bị cha ruột bỏ rơi, từ nhỏ đã phải thường xuyên sống trong cảnh bạo lực, nợ nần. Do đó, đối với Chi, tiền mới là thứ quan trọng nhất. Cô rất bực bội khi phải dành tiền để chăm lo cho gia đình chồng.</p>","tmdb_id":89816,"cast":["Gigi Wong","Mat Yeung","Huỳnh Đức Bân","Samantha Ko","Roxanne Tong","Billy Luk Wing-Kuen","Kirby Lam","Jerry Koo Ming-Wah","Lỗ Chấn Thuận","King Lam","Cecilia So Yan-Chee","Thomas Hin","Andy Shiu Cheuk-Yiu","Milkson Fong","Fanny Ip"],"director":[],"keywords":[],"cast_meta":[{"name":"Gigi Wong","name_vi":null,"name_original":"Gigi Wong","tmdb_id":1140989,"profile":"https://image.tmdb.org/t/p/w500/kdq98Xdx8yfUuhPZIHbRHrqnk3n.jpg","tmdb_url":"https://www.themoviedb.org/person/1140989"},{"name":"Mat Yeung","name_vi":null,"name_original":"Mat Yeung","tmdb_id":1588970,"profile":"https://image.tmdb.org/t/p/w500/1YLrCj101GPUsYFRW6MNrUnY06x.jpg","tmdb_url":"https://www.themoviedb.org/person/1588970"},{"name":"Huỳnh Đức Bân","name_vi":"Huỳnh Đức Bân","name_original":"Kenny Wong Tak-Ban","tmdb_id":70108,"profile":"https://image.tmdb.org/t/p/w500/fSSna59ChOc0OA8ju2xRf8jxOvT.jpg","tmdb_url":"https://www.themoviedb.org/person/70108"},{"name":"Samantha Ko","name_vi":null,"name_original":"Samantha Ko","tmdb_id":1173598,"profile":"https://image.tmdb.org/t/p/w500/trFirFO6af8zjdwbVNQI4YMpKf6.jpg","tmdb_url":"https://www.themoviedb.org/person/1173598"},{"name":"Roxanne Tong","name_vi":null,"name_original":"Roxanne Tong","tmdb_id":1967121,"profile":"https://image.tmdb.org/t/p/w500/zLbZGXfvhKbJpReSEECiedarfeg.jpg","tmdb_url":"https://www.themoviedb.org/person/1967121"},{"name":"Billy Luk Wing-Kuen","name_vi":null,"name_original":"Billy Luk Wing-Kuen","tmdb_id":1173596,"profile":"https://image.tmdb.org/t/p/w500/lLMSaX0ONn2rStJxb5V4VvbtHls.jpg","tmdb_url":"https://www.themoviedb.org/person/1173596"},{"name":"Kirby Lam","name_vi":null,"name_original":"Kirby Lam","tmdb_id":3007594,"profile":"https://image.tmdb.org/t/p/w500/szcaHjlB62vP5OmCjbD3ag5A5AG.jpg","tmdb_url":"https://www.themoviedb.org/person/3007594"},{"name":"Jerry Koo Ming-Wah","name_vi":null,"name_original":"Jerry Koo Ming-Wah","tmdb_id":1596646,"profile":"https://image.tmdb.org/t/p/w500/1IY02WvVvY8nASkxg5oeainXhNk.jpg","tmdb_url":"https://www.themoviedb.org/person/1596646"},{"name":"Lỗ Chấn Thuận","name_vi":"Lỗ Chấn Thuận","name_original":"Henry Lo","tmdb_id":1614785,"profile":"https://image.tmdb.org/t/p/w500/4SMud7dMceP8EY5rzFYhhGKidwf.jpg","tmdb_url":"https://www.themoviedb.org/person/1614785"},{"name":"King Lam","name_vi":null,"name_original":"King Lam","tmdb_id":3626789,"profile":"https://image.tmdb.org/t/p/w500/tIRDZYaWqqSMQoOq63BH3dMsCuv.jpg","tmdb_url":"https://www.themoviedb.org/person/3626789"},{"name":"Cecilia So Yan-Chee","name_vi":null,"name_original":"Cecilia So Yan-Chee","tmdb_id":3390465,"profile":"https://image.tmdb.org/t/p/w500/uIgBLgLISWJqBwfBC6sgmrqt7Hn.jpg","tmdb_url":"https://www.themoviedb.org/person/3390465"},{"name":"Thomas Hin","name_vi":null,"name_original":"Thomas Hin","tmdb_id":3522812,"profile":"https://image.tmdb.org/t/p/w500/itfk3rW1YgJDrCOCKRV5BI1WC5H.jpg","tmdb_url":"https://www.themoviedb.org/person/3522812"},{"name":"Andy Shiu Cheuk-Yiu","name_vi":null,"name_original":"Andy Shiu Cheuk-Yiu","tmdb_id":2064591,"profile":"https://image.tmdb.org/t/p/w500/sWYzhaslH5zDQylkAqaDJsTBMd2.jpg","tmdb_url":"https://www.themoviedb.org/person/2064591"},{"name":"Milkson Fong","name_vi":null,"name_original":"Milkson Fong","tmdb_id":2448435,"profile":"https://image.tmdb.org/t/p/w500/552iGNFbOAyYnSoc3NbE960bQ0K.jpg","tmdb_url":"https://www.themoviedb.org/person/2448435"},{"name":"Fanny Ip","name_vi":null,"name_original":"Fanny Ip","tmdb_id":3190539,"profile":"https://image.tmdb.org/t/p/w500/stVU34dd6TS85XHcNdBdGYPUUYd.jpg","tmdb_url":"https://www.themoviedb.org/person/3190539"}],"pubjs_url":"https://cdn.jsdelivr.net/gh/gotvtop102/pjs102@main/pubjs/do/doi-tac-hon-nhan.json"}