{"id":"63f0f0df7f562c619bbe202d","title":"Bóng Ma Goya","origin_name":"Goya's Ghosts","slug":"bong-ma-goya","thumb":"https://cdn.jsdelivr.net/gh/gotvtop102/goimg102@main/public/thumbs/bo/bong-ma-goya.webp","poster":"https://cdn.jsdelivr.net/gh/gotvtop102/goimg102@main/public/posters/bo/bong-ma-goya.webp","year":"2006","type":"single","genre":[{"name":"Chính kịch","slug":"chinh-kich"}],"country":[{"name":"Âu Mỹ","slug":"au-my"}],"lang_key":"Vietsub","episode_current":"Full","quality":"HD","modified":"2023-02-18T22:38:52.000Z","is_4k":false,"is_exclusive":false,"status":"completed","showtimes":"","chieurap":false,"sub_docquyen":false,"episodes":[{"name":"Vietsub #1","slug":"vietsub-1","server_name":"Vietsub #1","server_data":[{"name":"Full","slug":"full","link_embed":"https://vip.opstream14.com/share/d0deaa11f4e5050a6b9ff605ed3864fb","link_m3u8":"https://vip.opstream14.com/20230218/32171_94f4fb07/index.m3u8"}]}],"description":"<p>Họa sĩ Francisco Goya dính líu đến Tòa án Dị giáo Tây Ban Nha sau khi nàng thơ của ông, Inés, bị nhà thờ bắt giữ vì tội dị giáo. Gia đình cô hướng về anh ta, hy vọng rằng mối liên hệ của anh ta với Điều tra viên cuồng tín Lorenzo, người mà anh ta đang vẽ tranh, có thể giúp cô được thả.</p>","tmdb_id":11515,"cast":[],"director":[],"keywords":[],"tmdb":{"id":11515},"cast_meta":[],"tmdb_checked":false,"pubjs_url":"https://cdn.jsdelivr.net/gh/gotvtop102/pjs102@main/pubjs/bo/bong-ma-goya.json"}