{"id":"6409e2230fc1635bd468500c","title":"Tìm Kiếm","origin_name":"Missing","slug":"tim-kiem","thumb":"https://cdn.jsdelivr.net/gh/gotvtop102/goimg102@main/public/thumbs/ti/tim-kiem.webp","poster":"https://cdn.jsdelivr.net/gh/gotvtop102/goimg102@main/public/posters/ti/tim-kiem.webp","year":"2022","type":"single","genre":[{"name":"Hình Sự","slug":"hinh-su"},{"name":"Chính kịch","slug":"chinh-kich"},{"name":"Bí ẩn","slug":"bi-an"}],"country":[{"name":"Hàn Quốc","slug":"han-quoc"},{"name":"Nhật Bản","slug":"nhat-ban"}],"lang_key":"Vietsub","episode_current":"Full","quality":"HD","modified":"2023-03-09T20:41:55.000Z","is_4k":false,"is_exclusive":false,"status":"completed","showtimes":"","chieurap":false,"sub_docquyen":false,"episodes":[{"name":"Vietsub #1","slug":"vietsub-1","server_name":"Vietsub #1","server_data":[{"name":"Full","slug":"full","link_embed":"https://vip.opstream16.com/share/9f76ca9de39c2906f5e1e3f3ba38e255","link_m3u8":"https://vip.opstream16.com/20230309/32835_0edb7dae/index.m3u8"}]}],"description":"Sau cái chết của vợ, Santoshi chìm trong trầm cảm và nợ nần, trước sự kinh hoàng của con gái ông, học sinh trung học Kaede. Để xóa nợ, Santoshi quyết tâm truy tìm kẻ giết người hàng loạt đang bị truy nã nhằm lấy thưởng, trong sự ngỡ ngàng của con gái. Một ngày, Santoshi biến mất và Kaede vô hình lại rơi vào hành trình đi tìm bố.","tmdb_id":874476,"cast":[],"director":[],"keywords":[],"tmdb":{"id":874476},"cast_meta":[],"tmdb_checked":false,"pubjs_url":"https://cdn.jsdelivr.net/gh/gotvtop102/pjs102@main/pubjs/ti/tim-kiem.json"}