{"id":"629393b299cadeca03ec456b","title":"Vụ Án Sao Hỏa","origin_name":"2036 Origin Unknown","slug":"vu-an-sao-hoa","thumb":"https://cdn.jsdelivr.net/gh/gotvtop102/goimg102@main/public/thumbs/vu/vu-an-sao-hoa.webp","poster":"https://cdn.jsdelivr.net/gh/gotvtop102/goimg102@main/public/posters/vu/vu-an-sao-hoa.webp","year":2018,"type":"single","genre":[{"id":"620a2282e0fc277084dfd435","name":"Viễn Tưởng","slug":"vien-tuong"},{"id":"620a229be0fc277084dfd4dd","name":"Khoa Học","slug":"khoa-hoc"}],"country":[{"id":"620a2370e0fc277084dfd91e","name":"Anh","slug":"anh"}],"lang_key":"Vietsub","episode_current":"Full","quality":"HD","is_4k":false,"is_exclusive":false,"status":"completed","showtimes":"","chieurap":false,"sub_docquyen":false,"episodes":[{"server_name":"Vietsub #1","is_ai":false,"server_data":[{"name":"Full","slug":"full","filename":"vu-an-sao-hoa-2036-origin-unknown","link_embed":"https://vip.opstream12.com/share/5e84bd89fe45860ca1ebaf025f494461","link_m3u8":"https://vip.opstream12.com/20220529/16972_0553af55/index.m3u8"}]}],"time":"","description":"<p>Sau khi nhiệm vụ có người lái đầu tiên đến sao Hỏa kết thúc trong một vụ tai nạn chết người, người đứng đầu nhiệm vụ Mackenzie 'Mack' Wilson (Sackhoff) hỗ trợ một hệ thống trí tuệ nhân tạo, A.R.T.I. để điều tra sự việc.</p>","tmdb":{"type":"movie","id":"448916","season":null,"vote_average":4.704,"vote_count":280},"modified":"2022-05-29T15:39:30.000Z","cast":["Katee Sackhoff","Ray Fearon","Julie Cox"],"director":["Hasraf Dulull"],"cast_meta":[{"name":"Katee Sackhoff","name_vi":null,"name_original":"Katee Sackhoff"},{"name":"Ray Fearon","name_vi":null,"name_original":"Ray Fearon"},{"name":"Julie Cox","name_vi":null,"name_original":"Julie Cox"}],"keywords":[],"pubjs_url":"https://cdn.jsdelivr.net/gh/gotvtop102/pjs102@main/pubjs/vu/vu-an-sao-hoa.json"}