{"id":"63ede54095c7aea5f9457b63","title":"Trốn thì ngại mà thôi cũng kệ (Phần 2)","origin_name":"The Full-Time Wife Escapist (Season 2)","slug":"tron-thi-ngai-ma-thoi-cung-ke-phan-2","thumb":"https://cdn.jsdelivr.net/gh/gotvtop102/goimg102@main/public/thumbs/tr/tron-thi-ngai-ma-thoi-cung-ke-phan-2.webp","poster":"https://cdn.jsdelivr.net/gh/gotvtop102/goimg102@main/public/posters/tr/tron-thi-ngai-ma-thoi-cung-ke-phan-2.webp","year":"2016","type":"series","genre":[{"name":"Tâm Lý","slug":"tam-ly"}],"country":[{"name":"Nhật Bản","slug":"nhat-ban"},{"name":"Anh","slug":"anh"}],"lang_key":"Vietsub","episode_current":"Tập 1","quality":"HD","modified":"2023-02-16T15:11:44.000Z","is_4k":false,"is_exclusive":false,"status":"ongoing","showtimes":"","chieurap":false,"sub_docquyen":false,"episodes":[{"name":"Vietsub #1","slug":"vietsub-1","server_name":"Vietsub #1","server_data":[{"name":"1","slug":"1","link_embed":"https://vip.opstream16.com/share/29430ba87f428a5f10b3a531b0761f15","link_m3u8":"https://vip.opstream16.com/20230216/31737_23829d2c/index.m3u8"}]}],"description":"<p>Sau khi nhận được một số tin tức đáng mừng, Hiramasa và Mikuri quyết định chính thức kết hôn. Và rắc rối thực sự bắt đầu!</p>","tmdb_id":68293,"cast":[],"director":[],"keywords":[],"tmdb":{"id":68293},"cast_meta":[],"tmdb_checked":false,"pubjs_url":"https://cdn.jsdelivr.net/gh/gotvtop102/pjs102@main/pubjs/tr/tron-thi-ngai-ma-thoi-cung-ke-phan-2.json"}