{"id":"642e4db654695c9785d651c0","title":"Bụi Đời Gangnam","origin_name":"Gangnam Blues","slug":"bui-doi-gangnam","thumb":"https://cdn.jsdelivr.net/gh/gotvtop102/goimg102@main/public/thumbs/bu/bui-doi-gangnam.webp","poster":"https://cdn.jsdelivr.net/gh/gotvtop102/goimg102@main/public/posters/bu/bui-doi-gangnam.webp","year":"2015","type":"single","genre":[{"name":"Hành Động","slug":"hanh-dong"},{"name":"Hình Sự","slug":"hinh-su"},{"name":"Bí ẩn","slug":"bi-an"}],"country":[{"name":"Hàn Quốc","slug":"han-quoc"}],"lang_key":"Vietsub","episode_current":"Full","quality":"HD","modified":"2023-04-06T11:42:32.000Z","is_4k":false,"is_exclusive":false,"status":"completed","showtimes":"","chieurap":false,"sub_docquyen":false,"episodes":[{"name":"Vietsub #1","slug":"vietsub-1","server_name":"Vietsub #1","server_data":[{"name":"Full","slug":"full","link_embed":"https://vip.opstream14.com/share/868329656ab8bac9417b7536c7a65916","link_m3u8":"https://vip.opstream14.com/20230406/34806_3ede8357/index.m3u8"}]}],"description":"Bụi Đời Gangnam - Gangnam 1970 - Gangnam Blues: Lấy bối cảnh thành phố Seoul những năm 1970, bộ phim khắc họa sự đổi thay của con phố Gangnam, khi các doanh nghiệp bất động sản trải qua những biến cố lớn cùng những âm mưu của chính phủ và xã hội đen. Lee Min Ho sẽ đảm nhận vai chính mang số phận nghiệt ngã và sẽ có nhiều cảnh hành động.","tmdb_id":297721,"cast":[],"director":[],"keywords":[],"tmdb":{"id":297721},"cast_meta":[],"tmdb_checked":false,"pubjs_url":"https://cdn.jsdelivr.net/gh/gotvtop102/pjs102@main/pubjs/bu/bui-doi-gangnam.json"}