{"id":"6422a2b4162420646b024ac8","title":"Bước Chân Lạc Lối","origin_name":"On the Wrong Track","slug":"buoc-chan-lac-loi","thumb":"https://cdn.jsdelivr.net/gh/gotvtop102/goimg102@main/public/thumbs/bu/buoc-chan-lac-loi.webp","poster":"https://cdn.jsdelivr.net/gh/gotvtop102/goimg102@main/public/posters/bu/buoc-chan-lac-loi.webp","year":"1983","type":"single","genre":[{"name":"Chính kịch","slug":"chinh-kich"}],"country":[{"name":"Trung Quốc","slug":"trung-quoc"},{"name":"Hồng Kông","slug":"hong-kong"}],"lang_key":"Vietsub","episode_current":"Full","quality":"HD","modified":"2023-03-28T15:17:56.000Z","is_4k":false,"is_exclusive":false,"status":"completed","showtimes":"","chieurap":false,"sub_docquyen":false,"episodes":[{"name":"Vietsub #1","slug":"vietsub-1","server_name":"Vietsub #1","server_data":[{"name":"Full","slug":"full","link_embed":"https://vip.opstream15.com/share/da0276616a3e13b74f457ac86c15c3e8","link_m3u8":"https://vip.opstream15.com/20230328/36533_672e41a8/index.m3u8"}]}],"description":"Nhìn vào hai anh em, những người có sự nghiệp liều lĩnh với tư cách là thành viên băng đảng tạo ra xung đột với bạn bè, gia đình, cảnh sát, trường học và cuộc sống của họ.","tmdb_id":66208,"cast":[],"director":[],"keywords":[],"tmdb":{"id":66208},"cast_meta":[],"tmdb_checked":false,"pubjs_url":"https://cdn.jsdelivr.net/gh/gotvtop102/pjs102@main/pubjs/bu/buoc-chan-lac-loi.json"}