{"id":"626574a7489068f643a1153a","title":"Khu Vực Chết: Cuộc Săn Đuổi","origin_name":"Tribal Get Out Alive","slug":"khu-vuc-chet-cuoc-san-duoi","thumb":"https://cdn.jsdelivr.net/gh/gotvtop102/goimg102@main/public/thumbs/kh/khu-vuc-chet-cuoc-san-duoi.webp","poster":"https://cdn.jsdelivr.net/gh/gotvtop102/goimg102@main/public/posters/kh/khu-vuc-chet-cuoc-san-duoi.webp","year":"2020","type":"single","genre":[{"name":"Hành Động","slug":"hanh-dong"},{"name":"Phiêu Lưu","slug":"phieu-luu"},{"name":"Kinh Dị","slug":"kinh-di"}],"country":[{"name":"Anh","slug":"anh"}],"lang_key":"Vietsub","episode_current":"Full","quality":"HD","modified":"2023-04-11T19:38:10.000Z","is_4k":false,"is_exclusive":false,"status":"completed","showtimes":"","chieurap":false,"sub_docquyen":false,"episodes":[{"name":"Vietsub #1","slug":"vietsub-1","server_name":"Vietsub #1","server_data":[{"name":"Full","slug":"full","link_embed":"https://vip.opstream12.com/share/8ae7733f9bc11275e8d0a0fdabe5be0a","link_m3u8":"https://vip.opstream12.com/20220424/12202_678bf0ee/index.m3u8"}]}],"description":"<p>Khu Vực Chết: Cuộc Săn Đuổi – Tribal Get Out Alive (2020): Quân nhân ưu tú Caitlin Ross nghỉ việc sau khi mắc chứng PTSD. Cùng với cựu thành viên trong nhóm và người bạn thân Brad Johnson, họ đã chọn ‘cuộc sống dễ dàng’ và hiện lãnh đạo một công ty bảo mật nhỏ. Công ty được thuê bởi triệu phú trẻ tuổi, rắc rối Richard Kenning để giải tỏa và đảm bảo đất đai và tài sản mà ông mới được thừa kế. Những tin đồn và câu chuyện xung quanh vùng đất và các tòa nhà bị bác bỏ cho đến khi mọi người bắt đầu biến mất và cả đội bị nhốt không lối thoát. Rõ ràng là họ đang bị săn đuổi và cuộc chạy đua giành lấy sự sống đang diễn ra.</p>","tmdb_id":709621,"cast":[],"director":[],"keywords":[],"tmdb":{"id":709621},"cast_meta":[],"tmdb_checked":false,"pubjs_url":"https://cdn.jsdelivr.net/gh/gotvtop102/pjs102@main/pubjs/kh/khu-vuc-chet-cuoc-san-duoi.json"}