{"id":"6231d5313c735a9a446dde08","title":"Qua Nhanh Qua Nguy Hiem","origin_name":"The Fast and the Furious","slug":"qua-nhanh-qua-nguy-hiem","thumb":"https://cdn.jsdelivr.net/gh/gotvtop102/goimg102@main/public/thumbs/qu/qua-nhanh-qua-nguy-hiem.webp","poster":"https://cdn.jsdelivr.net/gh/gotvtop102/goimg102@main/public/posters/qu/qua-nhanh-qua-nguy-hiem.webp","year":"2001","type":"single","genre":[{"name":"Hành Động","slug":"hanh-dong"},{"name":"Kinh Dị","slug":"kinh-di"}],"country":[{"name":"Âu Mỹ","slug":"au-my"},{"name":"Đức","slug":"duc"}],"lang_key":"Vietsub","episode_current":"Full","quality":"HD","modified":"2023-04-11T18:16:38.000Z","is_4k":false,"is_exclusive":false,"status":"completed","showtimes":"","chieurap":false,"sub_docquyen":false,"episodes":[{"name":"Vietsub #1","slug":"vietsub-1","server_name":"Vietsub #1","server_data":[{"name":"Full","slug":"full","link_embed":"https://vip.opstream11.com/share/955cb567b6e38f4c6b3f28cc857fc38c","link_m3u8":"https://vip.opstream11.com/20220315/2054_7072464f/index.m3u8"},{"name":"Full","slug":"full","link_embed":"https://vip.opstream16.com/share/cdebf2bdf97feb83d4ecdc46f7c4630a","link_m3u8":"https://vip.opstream16.com/20230411/33796_976c8919/index.m3u8"}]}],"description":"<p>Cán bộ cảnh sát Los Angeles Brian O'Conner phải quyết định nơi lòng trung thành của mình thực sự nói dối khi anh ta bị say mê với thế giới đua xe trên đường phố mà anh ta đã được gửi bí mật để phá hủy.</p>","tmdb_id":9799,"cast":[],"director":[],"keywords":[],"tmdb":{"id":9799},"cast_meta":[],"tmdb_checked":false,"pubjs_url":"https://cdn.jsdelivr.net/gh/gotvtop102/pjs102@main/pubjs/qu/qua-nhanh-qua-nguy-hiem.json"}