{"id":"63e10e7bcaf0f6e22aece2b3","title":"Đại Pháo Thành Navarone","origin_name":"The Guns of Navarone","slug":"dai-phao-thanh-navarone","thumb":"https://cdn.jsdelivr.net/gh/gotvtop102/goimg102@main/public/thumbs/da/dai-phao-thanh-navarone.webp","poster":"https://cdn.jsdelivr.net/gh/gotvtop102/goimg102@main/public/posters/da/dai-phao-thanh-navarone.webp","year":"1961","type":"single","genre":[{"name":"Hành Động","slug":"hanh-dong"},{"name":"Chiến Tranh","slug":"chien-tranh"}],"country":[{"name":"Âu Mỹ","slug":"au-my"}],"lang_key":"Vietsub","episode_current":"Full","quality":"HD","modified":"2023-02-06T21:28:11.000Z","is_4k":false,"is_exclusive":false,"status":"completed","showtimes":"","chieurap":false,"sub_docquyen":false,"episodes":[{"name":"Vietsub #1","slug":"vietsub-1","server_name":"Vietsub #1","server_data":[{"name":"Full","slug":"full","link_embed":"https://vip.opstream14.com/share/ca4bd348a1b1db1a379686aaaf258f37","link_m3u8":"https://vip.opstream14.com/20230206/30516_74f04963/index.m3u8"}]}],"description":"<p>Một nhóm những kẻ phá hoại đồng minh được giao một nhiệm vụ bất khả thi: thâm nhập vào một hòn đảo bất khả xâm phạm do Đức Quốc xã nắm giữ và phá hủy hai khẩu súng trường tầm xa khổng lồ ngăn cản việc giải cứu 2.000 binh sĩ Anh bị mắc kẹt.</p>","tmdb_id":10911,"cast":[],"director":[],"keywords":[],"tmdb":{"id":10911},"cast_meta":[],"tmdb_checked":false,"pubjs_url":"https://cdn.jsdelivr.net/gh/gotvtop102/pjs102@main/pubjs/da/dai-phao-thanh-navarone.json"}