{"id":"6235c56c3d016a3b6717c26b","title":"Giải Mã Mê Cung","origin_name":"The Maze Runner","slug":"giai-ma-me-cung","thumb":"https://cdn.jsdelivr.net/gh/gotvtop102/goimg102@main/public/thumbs/gi/giai-ma-me-cung.webp","poster":"https://cdn.jsdelivr.net/gh/gotvtop102/goimg102@main/public/posters/gi/giai-ma-me-cung.webp","year":"2014","type":"single","genre":[{"name":"Hành Động","slug":"hanh-dong"},{"name":"Viễn Tưởng","slug":"vien-tuong"},{"name":"Khoa Học","slug":"khoa-hoc"},{"name":"Kinh Dị","slug":"kinh-di"}],"country":[{"name":"Âu Mỹ","slug":"au-my"},{"name":"Anh","slug":"anh"}],"lang_key":"Vietsub","episode_current":"Full","quality":"HD","modified":"2023-04-12T00:19:05.000Z","is_4k":false,"is_exclusive":false,"status":"completed","showtimes":"","chieurap":false,"sub_docquyen":false,"episodes":[{"name":"Vietsub #1","slug":"vietsub-1","server_name":"Vietsub #1","server_data":[{"name":"Full","slug":"full","link_embed":"https://vip.opstream12.com/share/ecf5631507a8aedcae34cef231aa7348","link_m3u8":"https://vip.opstream12.com/20220318/4159_7b7b88b7/index.m3u8"},{"name":"Full","slug":"full","link_embed":"https://vip.opstream16.com/share/8291147824f5712d2c342d34df21f193","link_m3u8":"https://vip.opstream16.com/20230412/33806_90d2519e/index.m3u8"}]}],"description":"<p>Thức tỉnh trong thang máy, nhớ không có gì trong quá khứ của mình, Thomas xuất hiện thành một thế giới của khoảng ba mươi chàng trai tuổi teen, tất cả không có ký ức trong quá khứ, những người đã học cách sống sót dưới một bộ quy tắc của riêng họ trong một môi trường hoàn toàn kín, tồn tại trên nông nghiệp của chính họ và quân nhu. Với một cậu bé mới đến mỗi ba mươi ngày, nhóm đã ở trong \"The Glade\" trong ba năm, cố gắng tìm cách trốn thoát qua mê cung bao quanh không gian sống của họ (được chú cây Cyborg tuần tra tên là 'Grievers'). Họ đã bắt đầu từ bỏ hy vọng khi một cô gái hôn mê đến với một ghi chú kỳ lạ, và thế giới của họ bắt đầu thay đổi với các chàng trai chia thành hai phe phái: những người sẵn sàng mạo hiểm cuộc sống của họ để trốn thoát và những người muốn treo lên những gì họ đã có và sống sót.</p>","tmdb_id":198663,"cast":[],"director":[],"keywords":[],"tmdb":{"id":198663},"cast_meta":[],"tmdb_checked":false,"pubjs_url":"https://cdn.jsdelivr.net/gh/gotvtop102/pjs102@main/pubjs/gi/giai-ma-me-cung.json"}